integer_partition_boltzmann/__init__.py
integer_partition_boltzmann/calculator.py
integer_partition_boltzmann-0.0.1.dist-info/LICENSE
integer_partition_boltzmann-0.0.1.dist-info/METADATA
integer_partition_boltzmann-0.0.1.dist-info/WHEEL
integer_partition_boltzmann-0.0.1.dist-info/top_level.txt
integer_partition_boltzmann-0.0.1.dist-info/RECORD
