Metadata-Version: 2.1
Name: integer-partition-boltzmann
Version: 0.0.1
Summary: A Python package for calculating Boltzmann distributions over integer partitions.
Home-page: https://github.com/juhdanad/integer-partition-boltzmann
Author: Dániel Juhász
Author-email: juhdanad@gmail.com
License: UNKNOWN
Project-URL: Bug Tracker, https://github.com/juhdanad/integer-partition-boltzmann/issues
Platform: UNKNOWN
Classifier: Programming Language :: Python :: 3
Classifier: License :: OSI Approved :: MIT License
Classifier: Operating System :: OS Independent
Requires-Python: >=3.6
License-File: LICENSE
Requires-Dist: numpy
